{"pLf6YQyEWTZAdNak/DOZuw==":"cross-400x545.jpg","QNBl1oLOOp5MbIkcAh6eBQ==":"cross-1-400x545.jpg","bdDFziYrymZ+dIMUT34AVw==":"cross-2-400x545.jpg","Qmya9N6iXU6joLn1Ws7IKA==":"cross-3-400x545.jpg","2ga+p0eYS0/ijwdN6MALvw==":"cross-4-400x545.jpg","gRnHjzF9UXYlWznX4Jh9Ow==":"cross-5-400x545.jpg","jwx54WDTr06lb1WEv6ngfA==":"cross-6-400x545.jpg","ClrVMa/hO0K/ZlKecQuwNw==":"son%20rise%202-122x127.png","tM+AQ37+S2WuQOMxsBN09g==":"son%20rise%202-122x127.png","UdeUNLkOxsFGKGkN1J4huA==":"cross-7-400x545.jpg","tVUdLlsd2EQGyXmwhlYhnw==":"cross-8-400x545.jpg","xmipHkJax28zjs4Sg2cULQ==":"cross-9-400x545.jpg","ZftuDmpryJyU2FJPSp5yQQ==":"cross-10-400x545.jpg","JwgTB/Mn2LHtNE6zszdwmA==":"cross-11-400x545.jpg","7h+qDR4mBLEBy6w0BeHHhw==":"cross-12-400x545.jpg","+0JaLJEF9al+S0CXLMNcVg==":"sunp0218-952x714.jpg","17V93etDZtJQhh4+4LvIpw==":"cross-13-400x545.jpg","uVOKakxpru3ft4IPXX4FTg==":"mbr-412x309.jpg","mPizMY9pmnKo+nRjxhNsRw==":"cross-14-400x545.jpg"}